B1/result/design.v
module PE #(
    parameter WEIGHT = 1
)(
    input wire clk,
    input wire rst,
    input wire [31:0] x_in,
    input wire [31:0] y_in,
    output reg [31:0] y_out
);
    reg [31:0] mult_result_reg;
    reg [31:0] y_reg;
    reg [31:0] sum;
    reg [31:0] x;

    always @(posedge clk or posedge rst) begin
        if (rst) begin
            mult_result_reg <= 32'd0;
            y_reg <= 32'd0;
            y_out <= 32'd0;
        end else begin
            x <= x_in;
            mult_result_reg <= x * WEIGHT;
            y_reg <= y_in;
            sum <= mult_result_reg + y_reg;
            y_out <= sum;
        end
    end
endmodule

module b1_systolic_array(
    input wire clk,
    input wire rst,
    input wire [31:0] x_in,
    input wire [31:0] y_in,
    output wire [31:0] y_out
);
    wire [31:0] y_sig1, y_sig2;

    // PE1: weight = 1
    PE #(.WEIGHT(1)) pe1 (
        .clk(clk),
        .rst(rst),
        .x_in(x_in),
        .y_in(y_in),
        .y_out(y_sig1)
    );

    // PE2: weight = 2
    PE #(.WEIGHT(2)) pe2 (
        .clk(clk),
        .rst(rst),
        .x_in(x_in),
        .y_in(y_sig1),
        .y_out(y_sig2)
    );

    // PE3: weight = 3
    PE #(.WEIGHT(3)) pe3 (
        .clk(clk),
        .rst(rst),
        .x_in(x_in),
        .y_in(y_sig2),
        .y_out(y_out)
    );
endmodule

B1/result/testbench.v
`timescale 1ns/1ps

module testbench;

reg clk;
reg rst;
reg [31:0] x_in;
reg [31:0] y_in;
wire [31:0] y_out;

// Instantiate the DUT (Design Under Test)
b1_systolic_array dut (
    .clk(clk),
    .rst(rst),
    .x_in(x_in),
    .y_in(y_in),
    .y_out(y_out)
);

// Clock generation: 10ns period (100MHz)
initial begin
    clk = 0;
    forever #5 clk = ~clk;
end

// Stimulus process
initial begin
    // Initialize inputs
    rst = 1;
    x_in = 0;
    y_in = 0;
    #15;
    rst = 0;

    // Cycle 1: Send x1
    x_in = 1;
    #10;

    // Cycle 2: Send x2
    x_in = 2;
    #10;

    // Cycle 3: Send x3
    x_in = 3;
    #10;

    // Cycle 4: Send x4
    x_in = 4;
    #10;

    // Cycle 5: Send x5
    x_in = 5;
    #10;

    // Flush pipeline
    x_in = 0;
    #70;

    // End simulation
    $finish;
end

// Monitor process
initial begin
    $display("Time\tx_in\ty_out");
    $monitor("%0t\t%d\t%d", $time, x_in, y_out);
end

// Optional: VCD waveform dump
initial begin
    $dumpfile("b1_systolic_array.vcd");
    $dumpvars(0, testbench);
end

endmodule

B1/result/b1_systolic_array.vcd
$date
	Sun Jun 22 12:35:48 2025
$end
$version
	Icarus Verilog
$end
$timescale
	1ps
$end
$scope module testbench $end
$var wire 32 ! y_out [31:0] $end
$var reg 1 " clk $end
$var reg 1 # rst $end
$var reg 32 $ x_in [31:0] $end
$var reg 32 % y_in [31:0] $end
$scope module dut $end
$var wire 1 " clk $end
$var wire 1 # rst $end
$var wire 32 & x_in [31:0] $end
$var wire 32 ' y_in [31:0] $end
$var wire 32 ( y_sig2 [31:0] $end
$var wire 32 ) y_sig1 [31:0] $end
$var wire 32 * y_out [31:0] $end
$scope module pe1 $end
$var wire 1 " clk $end
$var wire 1 # rst $end
$var wire 32 + x_in [31:0] $end
$var wire 32 , y_in [31:0] $end
$var parameter 32 - WEIGHT $end
$var reg 32 . mult_result_reg [31:0] $end
$var reg 32 / sum [31:0] $end
$var reg 32 0 x [31:0] $end
$var reg 32 1 y_out [31:0] $end
$var reg 32 2 y_reg [31:0] $end
$upscope $end
$scope module pe2 $end
$var wire 1 " clk $end
$var wire 1 # rst $end
$var wire 32 3 x_in [31:0] $end
$var wire 32 4 y_in [31:0] $end
$var parameter 32 5 WEIGHT $end
$var reg 32 6 mult_result_reg [31:0] $end
$var reg 32 7 sum [31:0] $end
$var reg 32 8 x [31:0] $end
$var reg 32 9 y_out [31:0] $end
$var reg 32 : y_reg [31:0] $end
$upscope $end
$scope module pe3 $end
$var wire 1 " clk $end
$var wire 1 # rst $end
$var wire 32 ; x_in [31:0] $end
$var wire 32 < y_in [31:0] $end
$var parameter 32 = WEIGHT $end
$var reg 32 > mult_result_reg [31:0] $end
$var reg 32 ? sum [31:0] $end
$var reg 32 @ x [31:0] $end
$var reg 32 A y_out [31:0] $end
$var reg 32 B y_reg [31:0] $end
$upscope $end
$upscope $end
$upscope $end
$enddefinitions $end
$comment Show the parameter values. $end
$dumpall
b11 =
b10 5
b1 -
$end
#0
$dumpvars
b0 B
b0 A
bx @
bx ?
b0 >
b0 <
b0 ;
b0 :
b0 9
bx 8
bx 7
b0 6
b0 4
b0 3
b0 2
b0 1
bx 0
bx /
b0 .
b0 ,
b0 +
b0 *
b0 )
b0 (
b0 '
b0 &
b0 %
b0 $
1#
0"
b0 !
$end
#5000
1"
#10000
0"
#15000
bx )
bx 1
bx 4
b0 /
bx .
b1 0
bx (
bx 9
bx <
b0 7
bx 6
b1 8
bx !
bx *
bx A
b0 ?
bx >
b1 @
1"
b1 $
b1 &
b1 +
b1 3
b1 ;
0#
#20000
0"
#25000
b0 !
b0 *
b0 A
bx ?
bx B
b11 >
b10 @
b0 (
b0 9
b0 <
bx 7
bx :
b10 6
b10 8
b0 )
b0 1
b0 4
bx /
b1 .
b10 0
1"
b10 $
b10 &
b10 +
b10 3
b10 ;
#30000
0"
#35000
bx )
bx 1
bx 4
b1 /
b10 .
b11 0
bx (
bx 9
bx <
b0 :
b100 6
b11 8
bx !
bx *
bx A
b0 B
b110 >
b11 @
1"
b11 $
b11 &
b11 +
b11 3
b11 ;
#40000
0"
#45000
b110 ?
bx B
b1001 >
b100 @
b100 7
bx :
b110 6
b100 8
b1 )
b1 1
b1 4
b10 /
b11 .
b100 0
1"
b100 $
b100 &
b100 +
b100 3
b100 ;
#50000
0"
#55000
b10 )
b10 1
b10 4
b11 /
b100 .
b101 0
b100 (
b100 9
b100 <
bx 7
b1 :
b1000 6
b101 8
b110 !
b110 *
b110 A
bx ?
b1100 >
b101 @
1"
b101 $
b101 &
b101 +
b101 3
b101 ;
#60000
0"
#65000
bx !
bx *
bx A
b100 B
b1111 >
b0 @
bx (
bx 9
bx <
b1001 7
b10 :
b1010 6
b0 8
b11 )
b11 1
b11 4
b100 /
b101 .
b0 0
1"
b0 $
b0 &
b0 +
b0 3
b0 ;
#70000
0"
#75000
b100 )
b100 1
b100 4
b101 /
b0 .
b1001 (
b1001 9
b1001 <
b1100 7
b11 :
b0 6
b10011 ?
bx B
b0 >
1"
#80000
0"
#85000
b10011 !
b10011 *
b10011 A
bx ?
b1001 B
b1100 (
b1100 9
b1100 <
b11 7
b100 :
b101 )
b101 1
b101 4
b0 /
1"
#90000
0"
#95000
b0 )
b0 1
b0 4
b11 (
b11 9
b11 <
b100 7
b101 :
bx !
bx *
bx A
b1001 ?
b1100 B
1"
#100000
0"
#105000
b1001 !
b1001 *
b1001 A
b1100 ?
b11 B
b100 (
b100 9
b100 <
b101 7
b0 :
1"
#110000
0"
#115000
b101 (
b101 9
b101 <
b0 7
b1100 !
b1100 *
b1100 A
b11 ?
b100 B
1"
#120000
0"
#125000
b11 !
b11 *
b11 A
b100 ?
b101 B
b0 (
b0 9
b0 <
1"
#130000
0"
#135000
b100 !
b100 *
b100 A
b101 ?
b0 B
1"
